{"type":"Topology","objects":{"units":{"type":"GeometryCollection","geometries":[{"type":"Polygon","properties":{"name":"Kompienga"},"id":"UV22","arcs":[[0,1,2,3]]},{"type":"Polygon","properties":{"name":"Gourma"},"id":"UV22","arcs":[[-4,4,5,6,7,8,9]]},{"type":"Polygon","properties":{"name":"Houet"},"id":"UV51","arcs":[[10,11,12,13,14,15,16]]},{"type":"Polygon","properties":{"name":"Kénédougou"},"id":"UV54","arcs":[[17,18,19,-15]]},{"type":"Polygon","properties":{"name":"Banwa"},"id":"UV58","arcs":[[20,21,-17,22]]},{"type":"Polygon","properties":{"name":"Kossi"},"id":"UV58","arcs":[[23,24,25,-21,26]]},{"type":"Polygon","properties":{"name":"Balé"},"id":"UV63","arcs":[[27,28,29,30,31]]},{"type":"Polygon","properties":{"name":"Mou Houn"},"id":"UV63","arcs":[[32,-32,33,-11,-22,-26,34]]},{"type":"Polygon","properties":{"name":"Oudalan"},"id":"UV33","arcs":[[35,36,37]]},{"type":"Polygon","properties":{"name":"Soum"},"id":"UV40","arcs":[[38,39,40,41,42,-37]]},{"type":"Polygon","properties":{"name":"Nayala"},"id":"UV73","arcs":[[43,44,-35,-25,45]]},{"type":"Polygon","properties":{"name":"Sourou"},"id":"UV73","arcs":[[46,47,48,-46,-24,49]]},{"type":"Polygon","properties":{"name":"Bam"},"id":"UV15","arcs":[[50,51,52,53,-41]]},{"type":"Polygon","properties":{"name":"Boulkiemdé"},"id":"UV19","arcs":[[54,55,56,57,58,59,60]]},{"type":"Polygon","properties":{"name":"Kourwéogo"},"id":"UV53","arcs":[[61,-55,62,63]]},{"type":"Polygon","properties":{"name":"Bazéga"},"id":"UV47","arcs":[[64,65,66,-57,67]]},{"type":"Polygon","properties":{"name":"Kadiogo"},"id":"UV53","arcs":[[68,-68,-56,-62,69]]},{"type":"Polygon","properties":{"name":"Oubritenga"},"id":"UV68","arcs":[[70,71,-70,-64,72]]},{"type":"Polygon","properties":{"name":"Passoré"},"id":"UV34","arcs":[[-52,73,-73,-63,-61,74,-44,-49,75,76]]},{"type":"Polygon","properties":{"name":"Zondoma"},"id":"UV34","arcs":[[-76,-48,77]]},{"type":"Polygon","properties":{"name":"Sanguié"},"id":"UV36","arcs":[[-60,78,-28,-33,-45,-75]]},{"type":"Polygon","properties":{"name":"Sissili"},"id":"UV72","arcs":[[79,80,81,-29,-79,-59,82]]},{"type":"Polygon","properties":{"name":"Ziro"},"id":"UV72","arcs":[[83,84,-83,-58,-67]]},{"type":"Polygon","properties":{"name":"Loroum"},"id":"UV15","arcs":[[-42,-54,85,86]]},{"type":"Polygon","properties":{"name":"Yatenga"},"id":"UV76","arcs":[[-53,-77,-78,-47,87,-86]]},{"type":"Polygon","properties":{"name":"Namentenga"},"id":"UV64","arcs":[[88,89,90,91,92]]},{"type":"Polygon","properties":{"name":"Sanmatenga"},"id":"UV70","arcs":[[-92,93,-71,-74,-51,-40,94]]},{"type":"Polygon","properties":{"name":"Boulgou"},"id":"UV49","arcs":[[95,-6,96,97,98,99,100]]},{"type":"Polygon","properties":{"name":"Koulpélogo"},"id":"UV49","arcs":[[-3,101,-97,-5]]},{"type":"Polygon","properties":{"name":"Ganzourgou"},"id":"UV50","arcs":[[-91,102,-101,103,-65,-69,-72,-94]]},{"type":"Polygon","properties":{"name":"Kouritenga"},"id":"UV28","arcs":[[-7,-96,-103,-90,104]]},{"type":"Polygon","properties":{"name":"Nahouri"},"id":"UV65","arcs":[[-99,105,-80,-85,106]]},{"type":"Polygon","properties":{"name":"Zoundwéogo"},"id":"UV44","arcs":[[-104,-100,-107,-84,-66]]},{"type":"Polygon","properties":{"name":"Bougouriba"},"id":"UV48","arcs":[[107,108,-13,109,110]]},{"type":"Polygon","properties":{"name":"Ioba"},"id":"UV48","arcs":[[-30,-82,111,112,-111,113]]},{"type":"Polygon","properties":{"name":"Tuy"},"id":"UV51","arcs":[[-31,-114,-110,-12,-34]]},{"type":"Polygon","properties":{"name":"Léraba"},"id":"UV54","arcs":[[114,115,-19]]},{"type":"Polygon","properties":{"name":"Komoé"},"id":"UV55","arcs":[[-14,-109,116,117,-115,-18]]},{"type":"Polygon","properties":{"name":"Poni"},"id":"UV69","arcs":[[118,119,120,-117,-108,-113]]},{"type":"Polygon","properties":{"name":"Gnagna"},"id":"UV21","arcs":[[121,-8,-105,-89,122,123]]},{"type":"Polygon","properties":{"name":"Komondjari"},"id":"UV21","arcs":[[124,-9,-122,125,126]]},{"type":"Polygon","properties":{"name":"Séno"},"id":"UV71","arcs":[[127,-123,-93,-95,-39,-36,128]]},{"type":"Polygon","properties":{"name":"Yagha"},"id":"UV71","arcs":[[-126,-124,-128,129]]},{"type":"Polygon","properties":{"name":"Tapoa"},"id":"UV42","arcs":[[-1,-10,-125,130]]},{"type":"Polygon","properties":{"name":"Noumbiel"},"id":"UV69","arcs":[[131,-120]]}]}},"arcs":[[[8533,4086],[244,-461]],[[8777,3625],[-385,-714],[-940,-40]],[[7452,2871],[195,1116]],[[7647,3987],[886,99]],[[7647,3987],[-606,157]],[[7041,4144],[-202,305]],[[6839,4449],[33,541]],[[6872,4990],[548,375]],[[7420,5365],[474,-185],[688,765]],[[8582,5945],[-49,-1859]],[[1948,4467],[40,-145]],[[1988,4322],[458,-1545]],[[2446,2777],[-175,-254]],[[2271,2523],[-1351,77]],[[920,2600],[308,1092],[-229,957]],[[999,4649],[100,61]],[[1099,4710],[849,-243]],[[920,2600],[-338,-68]],[[582,2532],[-561,379]],[[21,2911],[281,1386],[697,352]],[[1614,5865],[861,-433]],[[2475,5432],[-527,-965]],[[1099,4710],[515,1155]],[[2589,6637],[60,-671]],[[2649,5966],[-5,-63]],[[2644,5903],[-169,-471]],[[1614,5865],[346,1304],[629,-532]],[[3289,4677],[303,-779]],[[3592,3898],[-157,-661]],[[3435,3237],[-69,95]],[[3366,3332],[-920,826]],[[2446,4158],[843,519]],[[3388,5229],[-99,-552]],[[2446,4158],[-458,164]],[[2644,5903],[744,-674]],[[7234,8865],[-972,-514]],[[6262,8351],[-602,1188]],[[5660,9539],[409,457],[1185,-294],[-20,-837]],[[6262,8351],[-95,-302]],[[6167,8049],[-874,-407]],[[5293,7642],[-522,-17]],[[4771,7625],[-427,756]],[[4344,8381],[149,570],[1167,588]],[[3579,6214],[67,-335]],[[3646,5879],[-258,-650]],[[2649,5966],[930,248]],[[3276,7464],[429,-606]],[[3705,6858],[-120,-567]],[[3585,6291],[-6,-77]],[[2589,6637],[687,827]],[[5293,7642],[-213,-1310]],[[5080,6332],[-303,225]],[[4777,6557],[-172,738]],[[4605,7295],[166,330]],[[4526,5774],[152,-587]],[[4678,5187],[-63,-347]],[[4615,4840],[-216,-288]],[[4399,4552],[-250,-126]],[[4149,4426],[-18,-14]],[[4131,4412],[-72,1312]],[[4059,5724],[467,50]],[[4962,5767],[-284,-580]],[[4526,5774],[265,394]],[[4791,6168],[171,-401]],[[5636,4908],[221,-524]],[[5857,4384],[-581,-531]],[[5276,3853],[-877,699]],[[4615,4840],[1021,68]],[[5591,5041],[45,-133]],[[4962,5767],[629,-726]],[[5017,6174],[900,-669]],[[5917,5505],[-326,-464]],[[4791,6168],[226,6]],[[5080,6332],[-63,-158]],[[4059,5724],[-413,155]],[[3585,6291],[703,164]],[[4288,6455],[489,102]],[[3705,6858],[583,-403]],[[4131,4412],[-539,-514]],[[4972,3393],[220,-542]],[[5192,2851],[-1662,-50]],[[3530,2801],[-95,436]],[[4149,4426],[-122,-642],[945,-391]],[[5276,3853],[43,-86]],[[5319,3767],[-347,-374]],[[4605,7295],[-1009,1055]],[[3596,8350],[748,31]],[[3276,7464],[320,886]],[[6693,7216],[23,-1646]],[[6716,5570],[-513,-97]],[[6203,5473],[-74,301]],[[6129,5774],[81,2191]],[[6210,7965],[483,-749]],[[6129,5774],[-212,-269]],[[6167,8049],[43,-84]],[[6392,4563],[447,-114]],[[7041,4144],[-208,-1098]],[[6833,3046],[-743,-229]],[[6090,2817],[-93,355]],[[5997,3172],[-27,1126]],[[5970,4298],[422,265]],[[7452,2871],[-619,175]],[[6203,5473],[189,-910]],[[5970,4298],[-113,86]],[[6716,5570],[156,-580]],[[6090,2817],[-898,34]],[[5319,3767],[678,-595]],[[3121,2371],[-811,-170]],[[2310,2201],[-39,322]],[[2446,2777],[359,350]],[[2805,3127],[316,-756]],[[3530,2801],[-241,-482]],[[3289,2319],[-168,52]],[[2805,3127],[561,205]],[[582,2532],[-74,-946]],[[508,1586],[-508,231],[21,1094]],[[2310,2201],[-249,-1318]],[[2061,883],[-546,-503],[-1007,1206]],[[3289,2319],[166,-1088]],[[3455,1231],[-523,-323]],[[2932,908],[-871,-25]],[[7704,6262],[-284,-897]],[[6693,7216],[363,142]],[[7056,7358],[648,-1096]],[[8627,6059],[-45,-114]],[[7704,6262],[502,231]],[[8206,6493],[421,-434]],[[7609,7838],[-553,-480]],[[7234,8865],[375,-1027]],[[7609,7838],[571,-470],[26,-875]],[[8627,6059],[1017,-235],[355,-1421],[-474,-817],[-748,39]],[[3455,1231],[31,-1231],[-554,908]]],"transform":{"scale":[0.0007913538342834255,0.0005688593762376208],"translate":[-5.522578084999878,9.391882629000136]}}