{"type":"Topology","objects":{"units":{"type":"GeometryCollection","geometries":[{"type":"Polygon","properties":{"name":"Charlotte"},"id":"VC01","arcs":[[0,1,2,3,4]]},{"type":"Polygon","properties":{"name":"Saint Andrew"},"id":"VC02","arcs":[[5,6,7,-2]]},{"type":"Polygon","properties":{"name":"Saint David"},"id":"VC03","arcs":[[-4,8,9]]},{"type":"Polygon","properties":{"name":"Saint George"},"id":"VC04","arcs":[[10,-6,-1]]},{"type":"Polygon","properties":{"name":"Saint Patrick"},"id":"VC05","arcs":[[-3,-8,11,-9]]}]}},"arcs":[[[9653,7700],[-1703,237]],[[7950,7937],[-181,283]],[[7769,8220],[332,298]],[[8101,8518],[489,1470]],[[8590,9988],[1409,-901],[-346,-1387]],[[7950,7937],[-1345,-671]],[[6605,7266],[-994,291]],[[5611,7557],[2158,663]],[[8101,8518],[-2403,38]],[[5698,8556],[2892,1432]],[[9653,7700],[-3048,-434]],[[5611,7557],[87,999]]],"transform":{"scale":[0.0000335930403040284,0.0000795693176317525],"translate":[-61.459828253999916,12.585150458000172]}}